[
  {
    "id": 1,
    "title": "Shutter",
    "image": "https://encrypted-tbn0.gstatic.com/images?q=tbn:ANd9GcQLbLIlFjIwdM2LTrMoc5MwVZD4mtN7X8YK8A&s"
  },
  {
    "id": 2,
    "title": "Metal Gates",
    "image": "https://encrypted-tbn0.gstatic.com/images?q=tbn:ANd9GcRPk-uH-pf2teLXO1Z22hXdaY_OAyzOFr661A&s"
  },
  {
    "id": 3,
    "title": "Stainless Steel Gates",
    "image": "https://encrypted-tbn0.gstatic.com/images?q=tbn:ANd9GcQA8cKNva1T9z8lpeKJt3EjLLrVF-oPVCqeuQ&s"
  },
  {
    "id": 4,
    "title": "Railing & Grills",
    "image": "https://encrypted-tbn0.gstatic.com/images?q=tbn:ANd9GcTYh-xZjqv8aALQKdAzrGgVkOfd3FhN_rdYrg&s"
  },

  {
    "id": 5,
    "title": "Metal Furniture",
    "image": "https://encrypted-tbn0.gstatic.com/images?q=tbn:ANd9GcS6hEXmdSGhshMU5xKdTEmNh8eAIFM0w0FgMw&s"
  },
  {
    "id": 6,
    "title": "Sheds",
    "image": "https://encrypted-tbn0.gstatic.com/images?q=tbn:ANd9GcRM9c3JKJD7XgM36ttLSpNwfADdDlbSX-YYWA&s"
  },
  {
    "id": 7,
    "title": "Garden Pergola",
    "image": "https://encrypted-tbn0.gstatic.com/images?q=tbn:ANd9GcSORSiFKdSsD4njSFheFDg2pUHRS2C3tfk--g&s"
  },
  {
    "id": 56,
    "title": "Metal Canopy Frame",
    "description": "Framework for a metal canopy.",
    "image": "/d29.jpg"
  }
]